{"legislative_session": "119", "identifier": "HR 585", "title": "Supporting Veteran Families in Need Act", "from_organization": "~{\"classification\": \"lower\"}", "classification": ["bill"], "subject": [], "abstracts": [], "other_titles": [{"note": "", "title": "To amend title 38, United States Code, to make permanent the authority of the Secretary of Veterans Affairs to provide financial assistance for supportive services for very low-income veteran families in permanent housing."}], "other_identifiers": [], "actions": [{"description": "Referred to the Subcommittee on Economic Opportunity.", "date": "2025-02-25T05:00:00+00:00", "organization_id": "~{\"classification\": \"lower\"}", "classification": [], "related_entities": []}, {"description": "Referred to the House Committee on Veterans' Affairs.", "date": "2025-01-21T05:00:00+00:00", "organization_id": "~{\"classification\": \"lower\"}", "classification": ["referral-committee"], "related_entities": []}, {"description": "Introduced in House", "date": "2025-01-21T05:00:00+00:00", "organization_id": "~{\"classification\": \"lower\"}", "classification": ["introduction"], "related_entities": []}], "sponsorships": [{"name": "Ed Case", "classification": "cosponsor", "entity_type": "person", "primary": false, "person_id": "~{\"name\": \"Ed Case\"}", "organization_id": null}, {"name": "Susie Lee", "classification": "cosponsor", "entity_type": "person", "primary": false, "person_id": "~{\"name\": \"Susie Lee\"}", "organization_id": null}, {"name": "Nicole Malliotakis", "classification": "cosponsor", "entity_type": "person", "primary": false, "person_id": "~{\"name\": \"Nicole Malliotakis\"}", "organization_id": null}, {"name": "Patrick Ryan", "classification": "cosponsor", "entity_type": "person", "primary": false, "person_id": "~{\"name\": \"Patrick Ryan\"}", "organization_id": null}, {"name": "Donald G. Davis", "classification": "cosponsor", "entity_type": "person", "primary": false, "person_id": "~{\"name\": \"Donald G. Davis\"}", "organization_id": null}, {"name": "Joe Neguse", "classification": "cosponsor", "entity_type": "person", "primary": false, "person_id": "~{\"name\": \"Joe Neguse\"}", "organization_id": null}, {"name": "Eugene Simon Vindman", "classification": "cosponsor", "entity_type": "person", "primary": false, "person_id": "~{\"name\": \"Eugene Simon Vindman\"}", "organization_id": null}, {"name": "Nick LaLota", "classification": "primary", "entity_type": "person", "primary": true, "person_id": "~{\"name\": \"Nick LaLota\"}", "organization_id": null}], "related_bills": [], "versions": [{"note": "Introduced in House", "links": [{"url": "https://www.govinfo.gov/content/pkg/BILLS-119hr585ih/xml/BILLS-119hr585ih.xml", "media_type": "text/xml"}, {"url": "https://www.govinfo.gov/content/pkg/BILLS-119hr585ih/pdf/BILLS-119hr585ih.pdf", "media_type": "application/pdf"}], "date": "2025-01-21", "classification": ""}], "documents": [], "citations": [], "sources": [{"url": "https://www.govinfo.gov/bulkdata/BILLSTATUS/119/hr/BILLSTATUS-119hr585.xml", "note": ""}, {"url": "https://congress.gov/bill/119th-congress/house-bill/585", "note": ""}], "extras": {"cosponsor_bioguides": ["C001055", "L000590", "M000317", "R000579", "D000230", "N000191", "V000138"], "sponsor_bioguides": ["L000598"]}, "jurisdiction": {"id": "ocd-jurisdiction/country:us/government", "name": "United States", "classification": "country", "division_id": "ocd-division/country:us"}, "scraped_at": "2025-05-20T04:44:37+00:00", "_id": "2215d26c-3535-11f0-ad0e-7a6812ea020f"}