{"legislative_session": "104th", "identifier": "HB1629", "title": "MUNI ASSIST PERMIT REFORM ACT", "from_organization": "~{\"classification\": \"lower\"}", "classification": ["bill"], "subject": [], "abstracts": [{"note": "", "abstract": "Creates the Municipal Assistance and Permit Review Reform Act. Provides that, by January 1, 2027, each State agency that requires authorization or environmental review of municipal construction or public works projects shall develop a web portal to be posted on the agency's website for the purpose of enhancing review and promoting timely issuance of permits required. Specifies the information an agency must make available on its web portal. Provides that, if an applicant submits a completed permit application to an agency for a covered project in accordance with all applicable State and federal law and there is no final action by the agency, then (1) the application is automatically approved after 180 days if notice and opportunity for public hearing are not required by State or federal law; and (2) the application is automatically approved after 270 days if notice and opportunity for public hearing are required by State or federal law. Defines terms including \"covered project\". Effective immediately."}], "other_titles": [], "other_identifiers": [], "actions": [{"description": "Filed with the Clerk by Rep. Amy Briel", "date": "2025-01-23", "organization_id": "~{\"classification\": \"lower\"}", "classification": ["filing"], "related_entities": []}, {"description": "First Reading", "date": "2025-01-28", "organization_id": "~{\"classification\": \"lower\"}", "classification": ["reading-1"], "related_entities": []}, {"description": "Referred to Rules Committee", "date": "2025-01-28", "organization_id": "~{\"classification\": \"lower\"}", "classification": [], "related_entities": []}, {"description": "Assigned to Executive Committee", "date": "2025-02-18", "organization_id": "~{\"classification\": \"lower\"}", "classification": ["referral-committee"], "related_entities": []}, {"description": "Rule 19(a) / Re-referred to Rules Committee", "date": "2025-03-21", "organization_id": "~{\"classification\": \"lower\"}", "classification": [], "related_entities": []}], "sponsorships": [{"name": "Amy Briel", "classification": "primary", "entity_type": "person", "primary": true, "person_id": "~{\"chamber\": \"lower\", \"name\": \"Amy Briel\"}", "organization_id": null}], "related_bills": [], "versions": [{"note": "Introduced", "links": [{"url": "https://beta.ilga.gov/documents/legislation/104/HB/PDF/10400HB1629.pdf", "media_type": "application/pdf"}, {"url": "https://beta.ilga.gov/Legislation/BillStatus/FullText?LegDocId=198030&DocName=10400HB1629&DocNum=1629&DocTypeID=HB&LegID=158240&GAID=18&SessionID=114&SpecSess=&Session=&Print=1", "media_type": "text/html"}], "date": "", "classification": ""}], "documents": [], "citations": [], "sources": [{"url": "https://beta.ilga.gov/Legislation/BillStatus?DocNum=1629&GAID=18&DocTypeID=HB&LegId=158240&SessionID=114", "note": ""}], "extras": {}, "_id": "3bb06e4c-1728-11f0-9eaa-86812f74cec2"}