{"legislative_session": "104th", "identifier": "SB2070", "title": "VEH CD-CHANGE TO SPEED LIMIT", "from_organization": "~{\"classification\": \"upper\"}", "classification": ["bill"], "subject": [], "abstracts": [{"note": "", "abstract": "Amends the Illinois Vehicle Code. Provides that, on and after October 1, 2025, the default speed limit is 20 (instead of 30) miles per hour within an urban district, and 10 (instead of 15) miles per hour in an alley within an urban district. Requires, by September 1, 2025, the Secretary of State to communicate the speed limit change to every licensed driver in the State via direct postal mail and a broad statewide communications campaign. Provides that a county, municipality, or township with speed enforcement authority may only issue warnings for violations during the first 60 days after the change of the speed limit is enacted. Effective immediately."}], "other_titles": [], "other_identifiers": [], "actions": [{"description": "Filed with Secretary by Sen. Mike Porfirio", "date": "2025-02-06", "organization_id": "~{\"classification\": \"upper\"}", "classification": ["filing"], "related_entities": []}, {"description": "First Reading", "date": "2025-02-06", "organization_id": "~{\"classification\": \"upper\"}", "classification": ["reading-1"], "related_entities": []}, {"description": "Referred to Assignments", "date": "2025-02-06", "organization_id": "~{\"classification\": \"upper\"}", "classification": [], "related_entities": []}, {"description": "Added as Co-Sponsor Sen. Robert Peters", "date": "2025-02-25", "organization_id": "~{\"classification\": \"upper\"}", "classification": [], "related_entities": []}], "sponsorships": [{"name": "Mike Porfirio", "classification": "primary", "entity_type": "person", "primary": true, "person_id": "~{\"chamber\": \"upper\", \"name\": \"Mike Porfirio\"}", "organization_id": null}, {"name": "Robert Peters", "classification": "cosponsor", "entity_type": "person", "primary": false, "person_id": "~{\"chamber\": \"upper\", \"name\": \"Robert Peters\"}", "organization_id": null}], "related_bills": [], "versions": [{"note": "Introduced", "links": [{"url": "https://beta.ilga.gov/documents/legislation/104/SB/PDF/10400SB2070.pdf", "media_type": "application/pdf"}, {"url": "https://beta.ilga.gov/Legislation/BillStatus/FullText?LegDocId=201332&DocName=10400SB2070&DocNum=2070&DocTypeID=SB&LegID=161544&GAID=18&SessionID=114&SpecSess=&Session=&Print=1", "media_type": "text/html"}], "date": "", "classification": ""}], "documents": [], "citations": [], "sources": [{"url": "https://beta.ilga.gov/Legislation/BillStatus?DocNum=2070&GAID=18&DocTypeID=SB&LegId=161544&SessionID=114", "note": ""}], "extras": {}, "_id": "b63d0862-172a-11f0-9eaa-86812f74cec2"}