{"legislative_session": "104th", "identifier": "SB1899", "title": "FOID-DIVERSIONARY PROGRAM", "from_organization": "~{\"classification\": \"upper\"}", "classification": ["bill"], "subject": [], "abstracts": [{"note": "", "abstract": "Amends the Firearm Owners Identification Card Act. Provides that a person charged with certain weapon-related offenses under the Criminal Code of 2012 and sentenced to the First Time Weapons Offense Program under the Unified Code of Corrections or any other court-ordered diversionary program created by law or by a court of the State of Illinois may submit an application for a Firearm Owner's Identification Card before receiving a court order demonstrating completion of the program. Directs the Illinois State Police to issue a Firearm Owner's Identification Card to such a person upon receiving a court order demonstrating completion of the program, provided the person is otherwise eligible to receive a Firearm Owner's Identification Card. Specifies that a FOID application made under this provision shall be approved or denied within 10 business days of receiving a court order or written notification from a State's Attorney that the person completed a diversionary program."}], "other_titles": [], "other_identifiers": [], "actions": [{"description": "Filed with Secretary by Sen. Elgie R. Sims, Jr.", "date": "2025-02-06", "organization_id": "~{\"classification\": \"upper\"}", "classification": ["filing"], "related_entities": []}, {"description": "First Reading", "date": "2025-02-06", "organization_id": "~{\"classification\": \"upper\"}", "classification": ["reading-1"], "related_entities": []}, {"description": "Referred to Assignments", "date": "2025-02-06", "organization_id": "~{\"classification\": \"upper\"}", "classification": [], "related_entities": []}, {"description": "Added as Chief Co-Sponsor Sen. Mattie Hunter", "date": "2025-02-19", "organization_id": "~{\"classification\": \"upper\"}", "classification": [], "related_entities": []}, {"description": "Assigned to Executive", "date": "2025-03-12", "organization_id": "~{\"classification\": \"upper\"}", "classification": ["referral-committee"], "related_entities": []}, {"description": "Rule 2-10 Committee Deadline Established As April 4, 2025", "date": "2025-03-21", "organization_id": "~{\"classification\": \"upper\"}", "classification": [], "related_entities": []}], "sponsorships": [{"name": "Elgie R. Sims, Jr.", "classification": "primary", "entity_type": "person", "primary": true, "person_id": "~{\"chamber\": \"upper\", \"name\": \"Elgie R. Sims, Jr.\"}", "organization_id": null}, {"name": "Mattie Hunter", "classification": "cosponsor", "entity_type": "person", "primary": false, "person_id": "~{\"chamber\": \"upper\", \"name\": \"Mattie Hunter\"}", "organization_id": null}], "related_bills": [], "versions": [{"note": "Introduced", "links": [{"url": "https://beta.ilga.gov/documents/legislation/104/SB/PDF/10400SB1899.pdf", "media_type": "application/pdf"}, {"url": "https://beta.ilga.gov/Legislation/BillStatus/FullText?LegDocId=200972&DocName=10400SB1899&DocNum=1899&DocTypeID=SB&LegID=161184&GAID=18&SessionID=114&SpecSess=&Session=&Print=1", "media_type": "text/html"}], "date": "", "classification": ""}], "documents": [], "citations": [], "sources": [{"url": "https://beta.ilga.gov/Legislation/BillStatus?DocNum=1899&GAID=18&DocTypeID=SB&LegId=161184&SessionID=114", "note": ""}], "extras": {}, "_id": "9f31afe2-172a-11f0-9eaa-86812f74cec2"}