{"legislative_session": "104th", "identifier": "HB3577", "title": "FIREARM OFFENSE ENHANCED PENAL", "from_organization": "~{\"classification\": \"lower\"}", "classification": ["bill"], "subject": [], "abstracts": [{"note": "", "abstract": "Provides that the Act may be referred to as the Rafael Wordlaw Act. Amends the Criminal Code of 2012. Provides that \"machine gun\" includes any firearm that is modified or equipped with a forced reset trigger, including an auto-switch or binary switch. Provides that a person commits the offense of unlawful possession of weapons when the person knowingly sells, manufactures, purchases, possesses or carries any firearm that is modified or equipped with a high-capacity magazine. Provides that aggravated unlawful possession of a weapon while carrying or possessing a weapon that has been modified or equipped with a forced reset trigger, including an auto-switch or binary switch, or high-capacity magazine, is a Class X felony. Provides that a person who knowingly sells, offers to sell, or transfers an unserialized unfinished frame or receiver or unserialized firearm is guilty of a Class 2 (rather than a Class 4) felony for a first violation and is guilty of a Class 1 (rather than a Class 2) felony for a second or subsequent violation. Amends the Unified Code of Corrections. Permits the court to sentence a defendant to an extended term sentence for specified firearms violations. Provides that if a firearm used to commit the offense was outfitted with parts designed or intended for use in converting any weapon into a machine gun or a high-capacity magazine, 5 consecutive years shall be added on to the 15, 20, or 25 years to life added to the sentence. Defines terms."}], "other_titles": [], "other_identifiers": [], "actions": [{"description": "Filed with the Clerk by Rep. Michael J. Kelly", "date": "2025-02-07", "organization_id": "~{\"classification\": \"lower\"}", "classification": ["filing"], "related_entities": []}, {"description": "First Reading", "date": "2025-02-18", "organization_id": "~{\"classification\": \"lower\"}", "classification": ["reading-1"], "related_entities": []}, {"description": "Referred to Rules Committee", "date": "2025-02-18", "organization_id": "~{\"classification\": \"lower\"}", "classification": [], "related_entities": []}], "sponsorships": [{"name": "Michael J. Kelly", "classification": "primary", "entity_type": "person", "primary": true, "person_id": "~{\"chamber\": \"lower\", \"name\": \"Michael J. Kelly\"}", "organization_id": null}], "related_bills": [], "versions": [{"note": "Introduced", "links": [{"url": "https://beta.ilga.gov/documents/legislation/104/HB/PDF/10400HB3577.pdf", "media_type": "application/pdf"}, {"url": "https://beta.ilga.gov/Legislation/BillStatus/FullText?LegDocId=202056&DocName=10400HB3577&DocNum=3577&DocTypeID=HB&LegID=162268&GAID=18&SessionID=114&SpecSess=&Session=&Print=1", "media_type": "text/html"}], "date": "", "classification": ""}], "documents": [], "citations": [], "sources": [{"url": "https://beta.ilga.gov/Legislation/BillStatus?DocNum=3577&GAID=18&DocTypeID=HB&LegId=162268&SessionID=114", "note": ""}], "extras": {}, "_id": "3bb7d6ae-1729-11f0-9eaa-86812f74cec2"}