{"legislative_session": "104th", "identifier": "SB1694", "title": "TIF-DEVELOPER LOT INITIAL EAV", "from_organization": "~{\"classification\": \"upper\"}", "classification": ["bill"], "subject": [], "abstracts": [{"note": "", "abstract": "Amends the Tax Increment Allocation Redevelopment Act of the Illinois Municipal Code. Provides that if (1) 3 or more improved lots, blocks, tracts, or parcels of real property within a single redevelopment project area are purchased by a developer or a developer's parent company or wholly-owned subsidiary, or any combination thereof, within the 3 years prior to the date that the ordinance providing for the tax increment allocation was adopted by the municipality, and (2) an improvement on any of the lots, blocks, tracts, or parcels of real property is demolished or otherwise rendered uninhabitable, then the initial equalized assessed value for the lot, block, tract or parcel of real property shall be the equalized assessed value of the lot, block, tract, or parcel of real property on the date it was purchased by the developer, the developer's parent company, or the developer's wholly-owned subsidiary or purchased by any combination thereof. Limits the provisions to ordinances adopted after the effective date of the amendatory Act."}], "other_titles": [], "other_identifiers": [], "actions": [{"description": "Filed with Secretary by Sen. Robert F. Martwick", "date": "2025-02-05", "organization_id": "~{\"classification\": \"upper\"}", "classification": ["filing"], "related_entities": []}, {"description": "First Reading", "date": "2025-02-05", "organization_id": "~{\"classification\": \"upper\"}", "classification": ["reading-1"], "related_entities": []}, {"description": "Referred to Assignments", "date": "2025-02-05", "organization_id": "~{\"classification\": \"upper\"}", "classification": [], "related_entities": []}, {"description": "Assigned to Revenue", "date": "2025-02-18", "organization_id": "~{\"classification\": \"upper\"}", "classification": ["referral-committee"], "related_entities": []}, {"description": "Rule 2-10 Committee Deadline Established As April 11, 2025", "date": "2025-03-21", "organization_id": "~{\"classification\": \"upper\"}", "classification": [], "related_entities": []}], "sponsorships": [{"name": "Robert F. Martwick", "classification": "primary", "entity_type": "person", "primary": true, "person_id": "~{\"chamber\": \"upper\", \"name\": \"Robert F. Martwick\"}", "organization_id": null}], "related_bills": [], "versions": [{"note": "Introduced", "links": [{"url": "https://beta.ilga.gov/documents/legislation/104/SB/PDF/10400SB1694.pdf", "media_type": "application/pdf"}, {"url": "https://beta.ilga.gov/Legislation/BillStatus/FullText?LegDocId=200436&DocName=10400SB1694&DocNum=1694&DocTypeID=SB&LegID=160649&GAID=18&SessionID=114&SpecSess=&Session=&Print=1", "media_type": "text/html"}], "date": "", "classification": ""}], "documents": [], "citations": [], "sources": [{"url": "https://beta.ilga.gov/Legislation/BillStatus?DocNum=1694&GAID=18&DocTypeID=SB&LegId=160649&SessionID=114", "note": ""}], "extras": {}, "_id": "83e79760-172a-11f0-9eaa-86812f74cec2"}