{"legislative_session": "89R", "identifier": "HB 3859", "title": "Relating to motor vehicle franchised dealers and the reimbursement of motor vehicle franchised dealers by manufacturers and distributors for warranty, recall, over-the-air, and preparation and delivery work.", "from_organization": "~{\"classification\": \"lower\"}", "classification": ["bill"], "subject": ["Business & Commerce--General (I0050)", "MOTOR VEHICLE DEALERS (S1214)", "Occupational Regulation--Other Trades & Professions (I0541)", "Vehicles & Traffic--Equipment (I0855)", "Vehicles & Traffic--General (I0865)"], "abstracts": [], "other_titles": [], "other_identifiers": [], "actions": [{"description": "Filed", "date": "2025-03-05", "organization_id": "~{\"classification\": \"lower\"}", "classification": ["filing"], "related_entities": []}, {"description": "Read first time", "date": "2025-03-27", "organization_id": "~{\"classification\": \"lower\"}", "classification": ["introduction", "reading-1"], "related_entities": []}, {"description": "Referred to Transportation", "date": "2025-03-27", "organization_id": "~{\"classification\": \"lower\"}", "classification": ["referral-committee"], "related_entities": [{"name": "Transportation", "entity_type": "organization", "organization_id": null}]}, {"description": "Withdrawn from schedule", "date": "2025-04-17", "organization_id": "~{\"classification\": \"lower\"}", "classification": ["withdrawal"], "related_entities": []}, {"description": "Withdrawn from schedule", "date": "2025-04-22", "organization_id": "~{\"classification\": \"lower\"}", "classification": ["withdrawal"], "related_entities": []}, {"description": "Withdrawn from schedule", "date": "2025-05-01", "organization_id": "~{\"classification\": \"lower\"}", "classification": ["withdrawal"], "related_entities": []}], "sponsorships": [{"name": "Patterson", "classification": "primary", "entity_type": "person", "primary": true, "person_id": "~{\"name\": \"Patterson\"}", "organization_id": null}], "related_bills": [{"identifier": "SB 1917", "legislative_session": "89", "relation_type": "companion"}], "versions": [{"note": "Introduced", "links": [{"url": "http://capitol.texas.gov/tlodocs/89R/billtext/html/HB03859I.HTM", "media_type": "text/html"}, {"url": "http://capitol.texas.gov/tlodocs/89R/billtext/pdf/HB03859I.PDF", "media_type": "application/pdf"}], "date": "", "classification": ""}], "documents": [{"note": "Fiscal Note (Introduced)", "links": [{"url": "http://capitol.texas.gov/tlodocs/89R/fiscalNotes/html/HB03859I.HTM", "media_type": "text/html"}], "date": "", "classification": ""}], "citations": [], "sources": [{"url": "ftp://ftp.legis.state.tx.us/bills/89R/billhistory/house_bills/HB03800_HB03899/HB 3859.xml", "note": ""}, {"url": "https://capitol.texas.gov/BillLookup/History.aspx?LegSess=89R&Bill=HB3859", "note": ""}], "extras": {}, "jurisdiction": {"id": "ocd-jurisdiction/country:us/state:tx/government", "name": "Texas", "classification": "state", "division_id": "ocd-division/country:us/state:tx"}, "scraped_at": "2025-05-21T00:29:15+00:00", "_id": "a0641fe8-35da-11f0-946e-d2e317c0c502"}