{"legislative_session": "89R", "identifier": "HB 1539", "title": "Relating to seeking a waiver under Medicaid to provide a continuous period of eligibility under the program for certain children.", "from_organization": "~{\"classification\": \"lower\"}", "classification": ["bill"], "subject": ["HEALTH & HUMAN SERVICES COMMISSION (V0177)", "Health--Children's Insurance (I0388)", "Human Services--Child Services (I0895)", "MEDICAID (S4885)"], "abstracts": [], "other_titles": [], "other_identifiers": [], "actions": [{"description": "Filed", "date": "2024-12-06", "organization_id": "~{\"classification\": \"lower\"}", "classification": ["filing"], "related_entities": []}, {"description": "Read first time", "date": "2025-03-12", "organization_id": "~{\"classification\": \"lower\"}", "classification": ["introduction", "reading-1"], "related_entities": []}, {"description": "Referred to s/c on Dis Prev & Women's & Children's Health by Speaker", "date": "2025-03-12", "organization_id": "~{\"classification\": \"lower\"}", "classification": ["referral-committee"], "related_entities": [{"name": "s/c on Dis Prev & Women's & Children's Health by Speaker", "entity_type": "organization", "organization_id": null}]}], "sponsorships": [{"name": "Lalani", "classification": "primary", "entity_type": "person", "primary": true, "person_id": "~{\"name\": \"Lalani\"}", "organization_id": null}], "related_bills": [], "versions": [{"note": "Introduced", "links": [{"url": "http://capitol.texas.gov/tlodocs/89R/billtext/html/HB01539I.HTM", "media_type": "text/html"}, {"url": "http://capitol.texas.gov/tlodocs/89R/billtext/pdf/HB01539I.PDF", "media_type": "application/pdf"}], "date": "", "classification": ""}], "documents": [], "citations": [], "sources": [{"url": "ftp://ftp.legis.state.tx.us/bills/89R/billhistory/house_bills/HB01500_HB01599/HB 1539.xml", "note": ""}, {"url": "https://capitol.texas.gov/BillLookup/History.aspx?LegSess=89R&Bill=HB1539", "note": ""}], "extras": {}, "jurisdiction": {"id": "ocd-jurisdiction/country:us/state:tx/government", "name": "Texas", "classification": "state", "division_id": "ocd-division/country:us/state:tx"}, "scraped_at": "2025-05-21T00:06:31+00:00", "_id": "73661882-35d7-11f0-946e-d2e317c0c502"}