{"legislative_session": "119", "identifier": "HRES 238", "title": "Expressing the sense of the House of Representatives that every person has the basic right to emergency health care, including abortion care.", "from_organization": "~{\"classification\": \"lower\"}", "classification": ["resolution"], "subject": [], "abstracts": [], "other_titles": [], "other_identifiers": [], "actions": [{"description": "Referred to the House Committee on Energy and Commerce.", "date": "2025-03-21T04:00:00+00:00", "organization_id": "~{\"classification\": \"lower\"}", "classification": ["referral-committee"], "related_entities": []}, {"description": "Submitted in House", "date": "2025-03-21T04:00:00+00:00", "organization_id": "~{\"classification\": \"lower\"}", "classification": ["referral-committee"], "related_entities": []}], "sponsorships": [{"name": "Mikie Sherrill", "classification": "cosponsor", "entity_type": "person", "primary": false, "person_id": "~{\"name\": \"Mikie Sherrill\"}", "organization_id": null}, {"name": "Jake Auchincloss", "classification": "cosponsor", "entity_type": "person", "primary": false, "person_id": "~{\"name\": \"Jake Auchincloss\"}", "organization_id": null}, {"name": "Becca Balint", "classification": "cosponsor", "entity_type": "person", "primary": false, "person_id": "~{\"name\": \"Becca Balint\"}", "organization_id": null}, {"name": "Nanette Diaz Barrag\u00e1n", "classification": "cosponsor", "entity_type": "person", "primary": false, "person_id": "~{\"name\": \"Nanette Diaz Barrag\\u00e1n\"}", "organization_id": null}, {"name": "Wesley Bell", "classification": "cosponsor", "entity_type": "person", "primary": false, "person_id": "~{\"name\": \"Wesley Bell\"}", "organization_id": null}, {"name": "Donald S. Beyer", "classification": "cosponsor", "entity_type": "person", "primary": false, "person_id": "~{\"name\": \"Donald S. Beyer\"}", "organization_id": null}, {"name": "Shontel M. Brown", "classification": "cosponsor", "entity_type": "person", "primary": false, "person_id": "~{\"name\": \"Shontel M. Brown\"}", "organization_id": null}, {"name": "Julia Brownley", "classification": "cosponsor", "entity_type": "person", "primary": false, "person_id": "~{\"name\": \"Julia Brownley\"}", "organization_id": null}, {"name": "Nikki Budzinski", "classification": "cosponsor", "entity_type": "person", "primary": false, "person_id": "~{\"name\": \"Nikki Budzinski\"}", "organization_id": null}, {"name": "Andr\u00e9 Carson", "classification": "cosponsor", "entity_type": "person", "primary": false, "person_id": "~{\"name\": \"Andr\\u00e9 Carson\"}", "organization_id": null}, {"name": "Troy A. Carter", "classification": "cosponsor", "entity_type": "person", "primary": false, "person_id": "~{\"name\": \"Troy A. Carter\"}", "organization_id": null}, {"name": "Kathy Castor", "classification": "cosponsor", "entity_type": "person", "primary": false, "person_id": "~{\"name\": \"Kathy Castor\"}", "organization_id": null}, {"name": "Sheila Cherfilus-McCormick", "classification": "cosponsor", "entity_type": "person", "primary": false, "person_id": "~{\"name\": \"Sheila Cherfilus-McCormick\"}", "organization_id": null}, {"name": "Judy Chu", "classification": "cosponsor", "entity_type": "person", "primary": false, "person_id": "~{\"name\": \"Judy Chu\"}", "organization_id": null}, {"name": "Gilbert Ray Cisneros", "classification": "cosponsor", "entity_type": "person", "primary": false, "person_id": "~{\"name\": \"Gilbert Ray Cisneros\"}", "organization_id": null}, {"name": "Steve Cohen", "classification": "cosponsor", "entity_type": "person", "primary": false, "person_id": "~{\"name\": \"Steve Cohen\"}", "organization_id": null}, {"name": "Angie Craig", "classification": "cosponsor", "entity_type": "person", "primary": false, "person_id": "~{\"name\": \"Angie Craig\"}", "organization_id": null}, {"name": "Jasmine Crockett", "classification": "cosponsor", "entity_type": "person", "primary": false, "person_id": "~{\"name\": \"Jasmine Crockett\"}", "organization_id": null}, {"name": "Danny K. Davis", "classification": "cosponsor", "entity_type": "person", "primary": false, "person_id": "~{\"name\": \"Danny K. Davis\"}", "organization_id": null}, {"name": "Madeleine Dean", "classification": "cosponsor", "entity_type": "person", "primary": false, "person_id": "~{\"name\": \"Madeleine Dean\"}", "organization_id": null}, {"name": "Diana DeGette", "classification": "cosponsor", "entity_type": "person", "primary": false, "person_id": "~{\"name\": \"Diana DeGette\"}", "organization_id": null}, {"name": "Rosa L. DeLauro", "classification": "cosponsor", "entity_type": "person", "primary": false, "person_id": "~{\"name\": \"Rosa L. DeLauro\"}", "organization_id": null}, {"name": "Suzan K. DelBene", "classification": "cosponsor", "entity_type": "person", "primary": false, "person_id": "~{\"name\": \"Suzan K. DelBene\"}", "organization_id": null}, {"name": "Lloyd Doggett", "classification": "cosponsor", "entity_type": "person", "primary": false, "person_id": "~{\"name\": \"Lloyd Doggett\"}", "organization_id": null}, {"name": "Sarah Elfreth", "classification": "cosponsor", "entity_type": "person", "primary": false, "person_id": "~{\"name\": \"Sarah Elfreth\"}", "organization_id": null}, {"name": "Adriano Espaillat", "classification": "cosponsor", "entity_type": "person", "primary": false, "person_id": "~{\"name\": \"Adriano Espaillat\"}", "organization_id": null}, {"name": "Bill Foster", "classification": "cosponsor", "entity_type": "person", "primary": false, "person_id": "~{\"name\": \"Bill Foster\"}", "organization_id": null}, {"name": "Lois Frankel", "classification": "cosponsor", "entity_type": "person", "primary": false, "person_id": "~{\"name\": \"Lois Frankel\"}", "organization_id": null}, {"name": "Laura Friedman", "classification": "cosponsor", "entity_type": "person", "primary": false, "person_id": "~{\"name\": \"Laura Friedman\"}", "organization_id": null}, {"name": "Maxwell Frost", "classification": "cosponsor", "entity_type": "person", "primary": false, "person_id": "~{\"name\": \"Maxwell Frost\"}", "organization_id": null}, {"name": "Robert Garcia", "classification": "cosponsor", "entity_type": "person", "primary": false, "person_id": "~{\"name\": \"Robert Garcia\"}", "organization_id": null}, {"name": "Daniel S. Goldman", "classification": "cosponsor", "entity_type": "person", "primary": false, "person_id": "~{\"name\": \"Daniel S. Goldman\"}", "organization_id": null}, {"name": "Josh Gottheimer", "classification": "cosponsor", "entity_type": "person", "primary": false, "person_id": "~{\"name\": \"Josh Gottheimer\"}", "organization_id": null}, {"name": "Jahana Hayes", "classification": "cosponsor", "entity_type": "person", "primary": false, "person_id": "~{\"name\": \"Jahana Hayes\"}", "organization_id": null}, {"name": "Steven Horsford", "classification": "cosponsor", "entity_type": "person", "primary": false, "person_id": "~{\"name\": \"Steven Horsford\"}", "organization_id": null}, {"name": "Jared Huffman", "classification": "cosponsor", "entity_type": "person", "primary": false, "person_id": "~{\"name\": \"Jared Huffman\"}", "organization_id": null}, {"name": "Sara Jacobs", "classification": "cosponsor", "entity_type": "person", "primary": false, "person_id": "~{\"name\": \"Sara Jacobs\"}", "organization_id": null}, {"name": "Julie Johnson", "classification": "cosponsor", "entity_type": "person", "primary": false, "person_id": "~{\"name\": \"Julie Johnson\"}", "organization_id": null}, {"name": "Marcy Kaptur", "classification": "cosponsor", "entity_type": "person", "primary": false, "person_id": "~{\"name\": \"Marcy Kaptur\"}", "organization_id": null}, {"name": "Timothy M. Kennedy", "classification": "cosponsor", "entity_type": "person", "primary": false, "person_id": "~{\"name\": \"Timothy M. Kennedy\"}", "organization_id": null}, {"name": "Ro Khanna", "classification": "cosponsor", "entity_type": "person", "primary": false, "person_id": "~{\"name\": \"Ro Khanna\"}", "organization_id": null}, {"name": "Greg Landsman", "classification": "cosponsor", "entity_type": "person", "primary": false, "person_id": "~{\"name\": \"Greg Landsman\"}", "organization_id": null}, {"name": "Rick Larsen", "classification": "cosponsor", "entity_type": "person", "primary": false, "person_id": "~{\"name\": \"Rick Larsen\"}", "organization_id": null}, {"name": "John B. Larson", "classification": "cosponsor", "entity_type": "person", "primary": false, "person_id": "~{\"name\": \"John B. Larson\"}", "organization_id": null}, {"name": "Susie Lee", "classification": "cosponsor", "entity_type": "person", "primary": false, "person_id": "~{\"name\": \"Susie Lee\"}", "organization_id": null}, {"name": "Teresa Leger Fernandez", "classification": "cosponsor", "entity_type": "person", "primary": false, "person_id": "~{\"name\": \"Teresa Leger Fernandez\"}", "organization_id": null}, {"name": "Seth Magaziner", "classification": "cosponsor", "entity_type": "person", "primary": false, "person_id": "~{\"name\": \"Seth Magaziner\"}", "organization_id": null}, {"name": "Sarah McBride", "classification": "cosponsor", "entity_type": "person", "primary": false, "person_id": "~{\"name\": \"Sarah McBride\"}", "organization_id": null}, {"name": "April McClain Delaney", "classification": "cosponsor", "entity_type": "person", "primary": false, "person_id": "~{\"name\": \"April McClain Delaney\"}", "organization_id": null}, {"name": "James P. McGovern", "classification": "cosponsor", "entity_type": "person", "primary": false, "person_id": "~{\"name\": \"James P. McGovern\"}", "organization_id": null}, {"name": "LaMonica McIver", "classification": "cosponsor", "entity_type": "person", "primary": false, "person_id": "~{\"name\": \"LaMonica McIver\"}", "organization_id": null}, {"name": "Jennifer L. McClellan", "classification": "cosponsor", "entity_type": "person", "primary": false, "person_id": "~{\"name\": \"Jennifer L. McClellan\"}", "organization_id": null}, {"name": "Yassamin Ansari", "classification": "cosponsor", "entity_type": "person", "primary": false, "person_id": "~{\"name\": \"Yassamin Ansari\"}", "organization_id": null}, {"name": "Robert Menendez", "classification": "cosponsor", "entity_type": "person", "primary": false, "person_id": "~{\"name\": \"Robert Menendez\"}", "organization_id": null}, {"name": "Grace Meng", "classification": "cosponsor", "entity_type": "person", "primary": false, "person_id": "~{\"name\": \"Grace Meng\"}", "organization_id": null}, {"name": "Gwen Moore", "classification": "cosponsor", "entity_type": "person", "primary": false, "person_id": "~{\"name\": \"Gwen Moore\"}", "organization_id": null}, {"name": "Seth Moulton", "classification": "cosponsor", "entity_type": "person", "primary": false, "person_id": "~{\"name\": \"Seth Moulton\"}", "organization_id": null}, {"name": "Kevin Mullin", "classification": "cosponsor", "entity_type": "person", "primary": false, "person_id": "~{\"name\": \"Kevin Mullin\"}", "organization_id": null}, {"name": "Jerrold Nadler", "classification": "cosponsor", "entity_type": "person", "primary": false, "person_id": "~{\"name\": \"Jerrold Nadler\"}", "organization_id": null}, {"name": "Eleanor Holmes Norton", "classification": "cosponsor", "entity_type": "person", "primary": false, "person_id": "~{\"name\": \"Eleanor Holmes Norton\"}", "organization_id": null}, {"name": "Alexandria Ocasio-Cortez", "classification": "cosponsor", "entity_type": "person", "primary": false, "person_id": "~{\"name\": \"Alexandria Ocasio-Cortez\"}", "organization_id": null}, {"name": "Jimmy Panetta", "classification": "cosponsor", "entity_type": "person", "primary": false, "person_id": "~{\"name\": \"Jimmy Panetta\"}", "organization_id": null}, {"name": "Scott H. Peters", "classification": "cosponsor", "entity_type": "person", "primary": false, "person_id": "~{\"name\": \"Scott H. Peters\"}", "organization_id": null}, {"name": "Mark Pocan", "classification": "cosponsor", "entity_type": "person", "primary": false, "person_id": "~{\"name\": \"Mark Pocan\"}", "organization_id": null}, {"name": "Ayanna Pressley", "classification": "cosponsor", "entity_type": "person", "primary": false, "person_id": "~{\"name\": \"Ayanna Pressley\"}", "organization_id": null}, {"name": "Mike Quigley", "classification": "cosponsor", "entity_type": "person", "primary": false, "person_id": "~{\"name\": \"Mike Quigley\"}", "organization_id": null}, {"name": "Delia C. Ramirez", "classification": "cosponsor", "entity_type": "person", "primary": false, "person_id": "~{\"name\": \"Delia C. Ramirez\"}", "organization_id": null}, {"name": "Deborah K. Ross", "classification": "cosponsor", "entity_type": "person", "primary": false, "person_id": "~{\"name\": \"Deborah K. Ross\"}", "organization_id": null}, {"name": "Andrea Salinas", "classification": "cosponsor", "entity_type": "person", "primary": false, "person_id": "~{\"name\": \"Andrea Salinas\"}", "organization_id": null}, {"name": "Mary Gay Scanlon", "classification": "cosponsor", "entity_type": "person", "primary": false, "person_id": "~{\"name\": \"Mary Gay Scanlon\"}", "organization_id": null}, {"name": "Adam Smith", "classification": "cosponsor", "entity_type": "person", "primary": false, "person_id": "~{\"name\": \"Adam Smith\"}", "organization_id": null}, {"name": "Greg Stanton", "classification": "cosponsor", "entity_type": "person", "primary": false, "person_id": "~{\"name\": \"Greg Stanton\"}", "organization_id": null}, {"name": "Haley M. Stevens", "classification": "cosponsor", "entity_type": "person", "primary": false, "person_id": "~{\"name\": \"Haley M. Stevens\"}", "organization_id": null}, {"name": "Marilyn Strickland", "classification": "cosponsor", "entity_type": "person", "primary": false, "person_id": "~{\"name\": \"Marilyn Strickland\"}", "organization_id": null}, {"name": "Bradley Scott Schneider", "classification": "cosponsor", "entity_type": "person", "primary": false, "person_id": "~{\"name\": \"Bradley Scott Schneider\"}", "organization_id": null}, {"name": "Eric Swalwell", "classification": "cosponsor", "entity_type": "person", "primary": false, "person_id": "~{\"name\": \"Eric Swalwell\"}", "organization_id": null}, {"name": "Dina Titus", "classification": "cosponsor", "entity_type": "person", "primary": false, "person_id": "~{\"name\": \"Dina Titus\"}", "organization_id": null}, {"name": "Rashida Tlaib", "classification": "cosponsor", "entity_type": "person", "primary": false, "person_id": "~{\"name\": \"Rashida Tlaib\"}", "organization_id": null}, {"name": "Jill N. Tokuda", "classification": "cosponsor", "entity_type": "person", "primary": false, "person_id": "~{\"name\": \"Jill N. Tokuda\"}", "organization_id": null}, {"name": "Paul Tonko", "classification": "cosponsor", "entity_type": "person", "primary": false, "person_id": "~{\"name\": \"Paul Tonko\"}", "organization_id": null}, {"name": "Lori Trahan", "classification": "cosponsor", "entity_type": "person", "primary": false, "person_id": "~{\"name\": \"Lori Trahan\"}", "organization_id": null}, {"name": "Derek Tran", "classification": "cosponsor", "entity_type": "person", "primary": false, "person_id": "~{\"name\": \"Derek Tran\"}", "organization_id": null}, {"name": "Lauren Underwood", "classification": "cosponsor", "entity_type": "person", "primary": false, "person_id": "~{\"name\": \"Lauren Underwood\"}", "organization_id": null}, {"name": "Gabe Vasquez", "classification": "cosponsor", "entity_type": "person", "primary": false, "person_id": "~{\"name\": \"Gabe Vasquez\"}", "organization_id": null}, {"name": "Debbie Wasserman Schultz", "classification": "cosponsor", "entity_type": "person", "primary": false, "person_id": "~{\"name\": \"Debbie Wasserman Schultz\"}", "organization_id": null}, {"name": "Bonnie Watson Coleman", "classification": "cosponsor", "entity_type": "person", "primary": false, "person_id": "~{\"name\": \"Bonnie Watson Coleman\"}", "organization_id": null}, {"name": "Nikema Williams", "classification": "cosponsor", "entity_type": "person", "primary": false, "person_id": "~{\"name\": \"Nikema Williams\"}", "organization_id": null}, {"name": "Katherine M. Clark", "classification": "cosponsor", "entity_type": "person", "primary": false, "person_id": "~{\"name\": \"Katherine M. Clark\"}", "organization_id": null}, {"name": "George Whitesides", "classification": "cosponsor", "entity_type": "person", "primary": false, "person_id": "~{\"name\": \"George Whitesides\"}", "organization_id": null}, {"name": "Nydia M. Vel\u00e1zquez", "classification": "cosponsor", "entity_type": "person", "primary": false, "person_id": "~{\"name\": \"Nydia M. Vel\\u00e1zquez\"}", "organization_id": null}, {"name": "Dwight Evans", "classification": "cosponsor", "entity_type": "person", "primary": false, "person_id": "~{\"name\": \"Dwight Evans\"}", "organization_id": null}, {"name": "Norma J. Torres", "classification": "cosponsor", "entity_type": "person", "primary": false, "person_id": "~{\"name\": \"Norma J. Torres\"}", "organization_id": null}, {"name": "Johnny Olszewski", "classification": "cosponsor", "entity_type": "person", "primary": false, "person_id": "~{\"name\": \"Johnny Olszewski\"}", "organization_id": null}, {"name": "Frederica S. Wilson", "classification": "cosponsor", "entity_type": "person", "primary": false, "person_id": "~{\"name\": \"Frederica S. Wilson\"}", "organization_id": null}, {"name": "Doris O. Matsui", "classification": "cosponsor", "entity_type": "person", "primary": false, "person_id": "~{\"name\": \"Doris O. Matsui\"}", "organization_id": null}, {"name": "Betty McCollum", "classification": "cosponsor", "entity_type": "person", "primary": false, "person_id": "~{\"name\": \"Betty McCollum\"}", "organization_id": null}, {"name": "George Latimer", "classification": "cosponsor", "entity_type": "person", "primary": false, "person_id": "~{\"name\": \"George Latimer\"}", "organization_id": null}, {"name": "Joseph D. Morelle", "classification": "cosponsor", "entity_type": "person", "primary": false, "person_id": "~{\"name\": \"Joseph D. Morelle\"}", "organization_id": null}, {"name": "Lizzie Fletcher", "classification": "cosponsor", "entity_type": "person", "primary": false, "person_id": "~{\"name\": \"Lizzie Fletcher\"}", "organization_id": null}, {"name": "Juan Vargas", "classification": "cosponsor", "entity_type": "person", "primary": false, "person_id": "~{\"name\": \"Juan Vargas\"}", "organization_id": null}, {"name": "Eugene Simon Vindman", "classification": "cosponsor", "entity_type": "person", "primary": false, "person_id": "~{\"name\": \"Eugene Simon Vindman\"}", "organization_id": null}, {"name": "Kelly Morrison", "classification": "cosponsor", "entity_type": "person", "primary": false, "person_id": "~{\"name\": \"Kelly Morrison\"}", "organization_id": null}, {"name": "Robin L. Kelly", "classification": "cosponsor", "entity_type": "person", "primary": false, "person_id": "~{\"name\": \"Robin L. Kelly\"}", "organization_id": null}, {"name": "Maxine Dexter", "classification": "cosponsor", "entity_type": "person", "primary": false, "person_id": "~{\"name\": \"Maxine Dexter\"}", "organization_id": null}, {"name": "Salud O. Carbajal", "classification": "cosponsor", "entity_type": "person", "primary": false, "person_id": "~{\"name\": \"Salud O. Carbajal\"}", "organization_id": null}, {"name": "Christopher R. Deluzio", "classification": "cosponsor", "entity_type": "person", "primary": false, "person_id": "~{\"name\": \"Christopher R. Deluzio\"}", "organization_id": null}, {"name": "Emilia Strong Sykes", "classification": "primary", "entity_type": "person", "primary": true, "person_id": "~{\"name\": \"Emilia Strong Sykes\"}", "organization_id": null}], "related_bills": [], "versions": [{"note": "Introduced in House", "links": [{"url": "https://www.govinfo.gov/content/pkg/BILLS-119hres238ih/xml/BILLS-119hres238ih.xml", "media_type": "text/xml"}, {"url": "https://www.govinfo.gov/content/pkg/BILLS-119hres238ih/pdf/BILLS-119hres238ih.pdf", "media_type": "application/pdf"}], "date": "2025-03-21", "classification": ""}], "documents": [], "citations": [], "sources": [{"url": "https://www.govinfo.gov/bulkdata/BILLSTATUS/119/hres/BILLSTATUS-119hres238.xml", "note": ""}, {"url": "https://congress.gov/bill/119th-congress/house-resolution/238", "note": ""}], "extras": {"cosponsor_bioguides": ["S001207", "A000148", "B001318", "B001300", "B001324", "B001292", "B001313", "B001285", "B001315", "C001072", "C001125", "C001066", "C001127", "C001080", "C001123", "C001068", "C001119", "C001130", "D000096", "D000631", "D000197", "D000216", "D000617", "D000399", "E000301", "E000297", "F000454", "F000462", "F000483", "F000476", "G000598", "G000599", "G000583", "H001081", "H001066", "H001068", "J000305", "J000310", "K000009", "K000402", "K000389", "L000601", "L000560", "L000557", "L000590", "L000273", "M001223", "M001238", "M001232", "M000312", "M001229", "M001227", "A000381", "M001226", "M001188", "M001160", "M001196", "M001225", "N000002", "N000147", "O000172", "P000613", "P000608", "P000607", "P000617", "Q000023", "R000617", "R000305", "S001226", "S001205", "S000510", "S001211", "S001215", "S001159", "S001190", "S001193", "T000468", "T000481", "T000487", "T000469", "T000482", "T000491", "U000040", "V000136", "W000797", "W000822", "W000788", "C001101", "W000830", "V000081", "E000296", "T000474", "O000176", "W000808", "M001163", "M001143", "L000606", "M001206", "F000468", "V000130", "V000138", "M001234", "K000385", "D000635", "C001112", "D000530"], "sponsor_bioguides": ["S001223"]}, "jurisdiction": {"id": "ocd-jurisdiction/country:us/government", "name": "United States", "classification": "country", "division_id": "ocd-division/country:us"}, "scraped_at": "2025-05-21T00:27:28+00:00", "_id": "5ff87c7e-35da-11f0-8244-a6b901261a72"}