{"legislative_session": "119", "identifier": "S 853", "title": "INNOVATE Act", "from_organization": "~{\"classification\": \"upper\"}", "classification": ["bill"], "subject": [], "abstracts": [], "other_titles": [{"note": "", "title": "Investing in National Next-Generation Opportunities for Venture Acceleration and Technological Excellence"}, {"note": "", "title": "A bill to improve the SBIR and STTR programs under the Small Business Act, and for other purposes."}, {"note": "", "title": "This Act may be cited as the"}], "other_identifiers": [], "actions": [{"description": "Committee on Small Business and Entrepreneurship. Hearings held.", "date": "2025-03-05T05:00:00+00:00", "organization_id": "~{\"classification\": \"upper\"}", "classification": [], "related_entities": []}, {"description": "Read twice and referred to the Committee on Small Business and Entrepreneurship.", "date": "2025-03-05T05:00:00+00:00", "organization_id": "~{\"classification\": \"upper\"}", "classification": [], "related_entities": []}, {"description": "Introduced in Senate", "date": "2025-03-05T05:00:00+00:00", "organization_id": "~{\"classification\": \"upper\"}", "classification": ["introduction"], "related_entities": []}], "sponsorships": [{"name": "Joni Ernst", "classification": "primary", "entity_type": "person", "primary": true, "person_id": "~{\"name\": \"Joni Ernst\"}", "organization_id": null}], "related_bills": [], "versions": [{"note": "Introduced in Senate", "links": [{"url": "https://www.govinfo.gov/content/pkg/BILLS-119s853is/xml/BILLS-119s853is.xml", "media_type": "text/xml"}, {"url": "https://www.govinfo.gov/content/pkg/BILLS-119s853is/pdf/BILLS-119s853is.pdf", "media_type": "application/pdf"}], "date": "2025-03-05", "classification": ""}], "documents": [], "citations": [], "sources": [{"url": "https://www.govinfo.gov/bulkdata/BILLSTATUS/119/s/BILLSTATUS-119s853.xml", "note": ""}, {"url": "https://congress.gov/bill/119th-congress/senate-bill/853", "note": ""}], "extras": {"cosponsor_bioguides": [], "sponsor_bioguides": ["E000295"]}, "jurisdiction": {"id": "ocd-jurisdiction/country:us/government", "name": "United States", "classification": "country", "division_id": "ocd-division/country:us"}, "scraped_at": "2025-05-21T00:31:21+00:00", "_id": "eb189e60-35da-11f0-8244-a6b901261a72"}