{"legislative_session": "119", "identifier": "HR 1214", "title": "To require the name of military installation under jurisdiction of Secretary of the Army located in Fayetteville, North Carolina, to be known and designated as Fort Bragg, and for other purposes.", "from_organization": "~{\"classification\": \"lower\"}", "classification": ["bill"], "subject": [], "abstracts": [], "other_titles": [], "other_identifiers": [], "actions": [{"description": "Referred to the House Committee on Armed Services.", "date": "2025-02-11T05:00:00+00:00", "organization_id": "~{\"classification\": \"lower\"}", "classification": ["referral-committee"], "related_entities": []}, {"description": "Introduced in House", "date": "2025-02-11T05:00:00+00:00", "organization_id": "~{\"classification\": \"lower\"}", "classification": ["introduction"], "related_entities": []}], "sponsorships": [{"name": "Keith Self", "classification": "primary", "entity_type": "person", "primary": true, "person_id": "~{\"name\": \"Keith Self\"}", "organization_id": null}], "related_bills": [], "versions": [{"note": "Introduced in House", "links": [{"url": "https://www.govinfo.gov/content/pkg/BILLS-119hr1214ih/xml/BILLS-119hr1214ih.xml", "media_type": "text/xml"}, {"url": "https://www.govinfo.gov/content/pkg/BILLS-119hr1214ih/pdf/BILLS-119hr1214ih.pdf", "media_type": "application/pdf"}], "date": "2025-02-11", "classification": ""}], "documents": [], "citations": [], "sources": [{"url": "https://www.govinfo.gov/bulkdata/BILLSTATUS/119/hr/BILLSTATUS-119hr1214.xml", "note": ""}, {"url": "https://congress.gov/bill/119th-congress/house-bill/1214", "note": ""}], "extras": {"cosponsor_bioguides": [], "sponsor_bioguides": ["S001224"]}, "jurisdiction": {"id": "ocd-jurisdiction/country:us/government", "name": "United States", "classification": "country", "division_id": "ocd-division/country:us"}, "scraped_at": "2025-05-20T23:59:27+00:00", "_id": "75e780c4-35d6-11f0-8244-a6b901261a72"}