{"legislative_session": "119", "identifier": "HR 932", "title": "Protecting VA Employees Act", "from_organization": "~{\"classification\": \"lower\"}", "classification": ["bill"], "subject": [], "abstracts": [], "other_titles": [{"note": "", "title": "To amend titles 38 and 5, United States Code, to ensure that certain employees of the Department of Veterans Affairs are subject to the same removal, demotion, and suspension policies as other employees of the Federal Government, and for other purposes."}], "other_identifiers": [], "actions": [{"description": "Referred to the Subcommittee on Oversight and Investigations.", "date": "2025-03-06T05:00:00+00:00", "organization_id": "~{\"classification\": \"lower\"}", "classification": [], "related_entities": []}, {"description": "Referred to the Committee on Veterans' Affairs, and in addition to the Committee on Oversight and Government Reform, for a period to be subsequently determined by the Speaker, in each case for consideration of such provisions as fall within the jurisdiction of the committee concerned.", "date": "2025-02-04T05:00:00+00:00", "organization_id": "~{\"classification\": \"lower\"}", "classification": ["referral-committee"], "related_entities": []}, {"description": "Introduced in House", "date": "2025-02-04T05:00:00+00:00", "organization_id": "~{\"classification\": \"lower\"}", "classification": ["introduction"], "related_entities": []}], "sponsorships": [{"name": "Christopher R. Deluzio", "classification": "cosponsor", "entity_type": "person", "primary": false, "person_id": "~{\"name\": \"Christopher R. Deluzio\"}", "organization_id": null}, {"name": "Val T. Hoyle", "classification": "cosponsor", "entity_type": "person", "primary": false, "person_id": "~{\"name\": \"Val T. Hoyle\"}", "organization_id": null}, {"name": "Andrea Salinas", "classification": "cosponsor", "entity_type": "person", "primary": false, "person_id": "~{\"name\": \"Andrea Salinas\"}", "organization_id": null}, {"name": "Brian K. Fitzpatrick", "classification": "primary", "entity_type": "person", "primary": true, "person_id": "~{\"name\": \"Brian K. Fitzpatrick\"}", "organization_id": null}], "related_bills": [], "versions": [{"note": "Introduced in House", "links": [{"url": "https://www.govinfo.gov/content/pkg/BILLS-119hr932ih/xml/BILLS-119hr932ih.xml", "media_type": "text/xml"}, {"url": "https://www.govinfo.gov/content/pkg/BILLS-119hr932ih/pdf/BILLS-119hr932ih.pdf", "media_type": "application/pdf"}], "date": "2025-02-04", "classification": ""}], "documents": [], "citations": [], "sources": [{"url": "https://www.govinfo.gov/bulkdata/BILLSTATUS/119/hr/BILLSTATUS-119hr932.xml", "note": ""}, {"url": "https://congress.gov/bill/119th-congress/house-bill/932", "note": ""}], "extras": {"cosponsor_bioguides": ["D000530", "H001094", "S001226"], "sponsor_bioguides": ["F000466"]}, "jurisdiction": {"id": "ocd-jurisdiction/country:us/government", "name": "United States", "classification": "country", "division_id": "ocd-division/country:us"}, "scraped_at": "2025-05-20T23:56:34+00:00", "_id": "0f0ff5de-35d6-11f0-8244-a6b901261a72"}