{"legislative_session": "119", "identifier": "HR 3373", "title": "To create a system to report the movement of firearm parts across State lines, and for other purposes.", "from_organization": "~{\"classification\": \"lower\"}", "classification": ["bill"], "subject": [], "abstracts": [], "other_titles": [], "other_identifiers": [], "actions": [{"description": "Referred to the House Committee on the Judiciary.", "date": "2025-05-13T04:00:00+00:00", "organization_id": "~{\"classification\": \"lower\"}", "classification": ["referral-committee"], "related_entities": []}, {"description": "Introduced in House", "date": "2025-05-13T04:00:00+00:00", "organization_id": "~{\"classification\": \"lower\"}", "classification": ["introduction"], "related_entities": []}], "sponsorships": [{"name": "Eleanor Holmes Norton", "classification": "cosponsor", "entity_type": "person", "primary": false, "person_id": "~{\"name\": \"Eleanor Holmes Norton\"}", "organization_id": null}, {"name": "Henry C. \"Hank\" Johnson", "classification": "cosponsor", "entity_type": "person", "primary": false, "person_id": "~{\"name\": \"Henry C. \\\"Hank\\\" Johnson\"}", "organization_id": null}, {"name": "Greg Casar", "classification": "cosponsor", "entity_type": "person", "primary": false, "person_id": "~{\"name\": \"Greg Casar\"}", "organization_id": null}, {"name": "Sarah McBride", "classification": "cosponsor", "entity_type": "person", "primary": false, "person_id": "~{\"name\": \"Sarah McBride\"}", "organization_id": null}, {"name": "Raja Krishnamoorthi", "classification": "cosponsor", "entity_type": "person", "primary": false, "person_id": "~{\"name\": \"Raja Krishnamoorthi\"}", "organization_id": null}, {"name": "Robin L. Kelly", "classification": "cosponsor", "entity_type": "person", "primary": false, "person_id": "~{\"name\": \"Robin L. Kelly\"}", "organization_id": null}, {"name": "Madeleine Dean", "classification": "cosponsor", "entity_type": "person", "primary": false, "person_id": "~{\"name\": \"Madeleine Dean\"}", "organization_id": null}, {"name": "Robert Garcia", "classification": "cosponsor", "entity_type": "person", "primary": false, "person_id": "~{\"name\": \"Robert Garcia\"}", "organization_id": null}, {"name": "Yassamin Ansari", "classification": "cosponsor", "entity_type": "person", "primary": false, "person_id": "~{\"name\": \"Yassamin Ansari\"}", "organization_id": null}, {"name": "Derek Tran", "classification": "cosponsor", "entity_type": "person", "primary": false, "person_id": "~{\"name\": \"Derek Tran\"}", "organization_id": null}, {"name": "Mike Levin", "classification": "cosponsor", "entity_type": "person", "primary": false, "person_id": "~{\"name\": \"Mike Levin\"}", "organization_id": null}, {"name": "Suzanne Bonamici", "classification": "cosponsor", "entity_type": "person", "primary": false, "person_id": "~{\"name\": \"Suzanne Bonamici\"}", "organization_id": null}, {"name": "Emily Randall", "classification": "cosponsor", "entity_type": "person", "primary": false, "person_id": "~{\"name\": \"Emily Randall\"}", "organization_id": null}, {"name": "Nydia M. Vel\u00e1zquez", "classification": "cosponsor", "entity_type": "person", "primary": false, "person_id": "~{\"name\": \"Nydia M. Vel\\u00e1zquez\"}", "organization_id": null}, {"name": "Danny K. Davis", "classification": "cosponsor", "entity_type": "person", "primary": false, "person_id": "~{\"name\": \"Danny K. Davis\"}", "organization_id": null}, {"name": "Veronica Escobar", "classification": "cosponsor", "entity_type": "person", "primary": false, "person_id": "~{\"name\": \"Veronica Escobar\"}", "organization_id": null}, {"name": "Daniel S. Goldman", "classification": "cosponsor", "entity_type": "person", "primary": false, "person_id": "~{\"name\": \"Daniel S. Goldman\"}", "organization_id": null}, {"name": "LaMonica McIver", "classification": "cosponsor", "entity_type": "person", "primary": false, "person_id": "~{\"name\": \"LaMonica McIver\"}", "organization_id": null}, {"name": "Andrea Salinas", "classification": "cosponsor", "entity_type": "person", "primary": false, "person_id": "~{\"name\": \"Andrea Salinas\"}", "organization_id": null}, {"name": "Dave Min", "classification": "cosponsor", "entity_type": "person", "primary": false, "person_id": "~{\"name\": \"Dave Min\"}", "organization_id": null}, {"name": "Shri Thanedar", "classification": "cosponsor", "entity_type": "person", "primary": false, "person_id": "~{\"name\": \"Shri Thanedar\"}", "organization_id": null}, {"name": "Julia Brownley", "classification": "cosponsor", "entity_type": "person", "primary": false, "person_id": "~{\"name\": \"Julia Brownley\"}", "organization_id": null}, {"name": "Salud O. Carbajal", "classification": "cosponsor", "entity_type": "person", "primary": false, "person_id": "~{\"name\": \"Salud O. Carbajal\"}", "organization_id": null}, {"name": "Timothy M. Kennedy", "classification": "cosponsor", "entity_type": "person", "primary": false, "person_id": "~{\"name\": \"Timothy M. Kennedy\"}", "organization_id": null}, {"name": "Sarah Elfreth", "classification": "cosponsor", "entity_type": "person", "primary": false, "person_id": "~{\"name\": \"Sarah Elfreth\"}", "organization_id": null}, {"name": "Valerie P. Foushee", "classification": "cosponsor", "entity_type": "person", "primary": false, "person_id": "~{\"name\": \"Valerie P. Foushee\"}", "organization_id": null}, {"name": "Wesley Bell", "classification": "cosponsor", "entity_type": "person", "primary": false, "person_id": "~{\"name\": \"Wesley Bell\"}", "organization_id": null}, {"name": "Jennifer L. McClellan", "classification": "cosponsor", "entity_type": "person", "primary": false, "person_id": "~{\"name\": \"Jennifer L. McClellan\"}", "organization_id": null}, {"name": "Jill N. Tokuda", "classification": "primary", "entity_type": "person", "primary": true, "person_id": "~{\"name\": \"Jill N. Tokuda\"}", "organization_id": null}], "related_bills": [], "versions": [], "documents": [], "citations": [], "sources": [{"url": "https://www.govinfo.gov/bulkdata/BILLSTATUS/119/hr/BILLSTATUS-119hr3373.xml", "note": ""}, {"url": "https://congress.gov/bill/119th-congress/house-bill/3373", "note": ""}], "extras": {"cosponsor_bioguides": ["N000147", "J000288", "C001131", "M001238", "K000391", "K000385", "D000631", "G000598", "A000381", "T000491", "L000593", "B001278", "R000621", "V000081", "D000096", "E000299", "G000599", "M001229", "S001226", "M001241", "T000488", "B001285", "C001112", "K000402", "E000301", "F000477", "B001324", "M001227"], "sponsor_bioguides": ["T000487"]}, "jurisdiction": {"id": "ocd-jurisdiction/country:us/government", "name": "United States", "classification": "country", "division_id": "ocd-division/country:us"}, "scraped_at": "2025-05-21T00:22:06+00:00", "_id": "a02607f4-35d9-11f0-8244-a6b901261a72"}