{"legislative_session": "119", "identifier": "HRES 173", "title": "Restoring the promise of freedom: honoring, preserving, and investing in Freedmen's Settlements.", "from_organization": "~{\"classification\": \"lower\"}", "classification": ["resolution"], "subject": [], "abstracts": [], "other_titles": [], "other_identifiers": [], "actions": [{"description": "Referred to the House Committee on the Judiciary.", "date": "2025-02-27T05:00:00+00:00", "organization_id": "~{\"classification\": \"lower\"}", "classification": ["referral-committee"], "related_entities": []}], "sponsorships": [{"name": "Rashida Tlaib", "classification": "cosponsor", "entity_type": "person", "primary": false, "person_id": "~{\"name\": \"Rashida Tlaib\"}", "organization_id": null}, {"name": "Jonathan L. Jackson", "classification": "cosponsor", "entity_type": "person", "primary": false, "person_id": "~{\"name\": \"Jonathan L. Jackson\"}", "organization_id": null}, {"name": "Alexandria Ocasio-Cortez", "classification": "cosponsor", "entity_type": "person", "primary": false, "person_id": "~{\"name\": \"Alexandria Ocasio-Cortez\"}", "organization_id": null}, {"name": "Joyce Beatty", "classification": "cosponsor", "entity_type": "person", "primary": false, "person_id": "~{\"name\": \"Joyce Beatty\"}", "organization_id": null}, {"name": "Ayanna Pressley", "classification": "cosponsor", "entity_type": "person", "primary": false, "person_id": "~{\"name\": \"Ayanna Pressley\"}", "organization_id": null}, {"name": "Gwen Moore", "classification": "cosponsor", "entity_type": "person", "primary": false, "person_id": "~{\"name\": \"Gwen Moore\"}", "organization_id": null}, {"name": "LaMonica McIver", "classification": "cosponsor", "entity_type": "person", "primary": false, "person_id": "~{\"name\": \"LaMonica McIver\"}", "organization_id": null}, {"name": "Bonnie Watson Coleman", "classification": "cosponsor", "entity_type": "person", "primary": false, "person_id": "~{\"name\": \"Bonnie Watson Coleman\"}", "organization_id": null}, {"name": "Henry C. \"Hank\" Johnson", "classification": "cosponsor", "entity_type": "person", "primary": false, "person_id": "~{\"name\": \"Henry C. \\\"Hank\\\" Johnson\"}", "organization_id": null}, {"name": "Delia C. Ramirez", "classification": "cosponsor", "entity_type": "person", "primary": false, "person_id": "~{\"name\": \"Delia C. Ramirez\"}", "organization_id": null}, {"name": "Robin L. Kelly", "classification": "cosponsor", "entity_type": "person", "primary": false, "person_id": "~{\"name\": \"Robin L. Kelly\"}", "organization_id": null}, {"name": "Shontel M. Brown", "classification": "cosponsor", "entity_type": "person", "primary": false, "person_id": "~{\"name\": \"Shontel M. Brown\"}", "organization_id": null}, {"name": "Frederica S. Wilson", "classification": "cosponsor", "entity_type": "person", "primary": false, "person_id": "~{\"name\": \"Frederica S. Wilson\"}", "organization_id": null}, {"name": "Maxwell Frost", "classification": "cosponsor", "entity_type": "person", "primary": false, "person_id": "~{\"name\": \"Maxwell Frost\"}", "organization_id": null}, {"name": "Jill N. Tokuda", "classification": "cosponsor", "entity_type": "person", "primary": false, "person_id": "~{\"name\": \"Jill N. Tokuda\"}", "organization_id": null}, {"name": "Sydney Kamlager-Dove", "classification": "primary", "entity_type": "person", "primary": true, "person_id": "~{\"name\": \"Sydney Kamlager-Dove\"}", "organization_id": null}], "related_bills": [], "versions": [{"note": "Introduced in House", "links": [{"url": "https://www.govinfo.gov/content/pkg/BILLS-119hres173ih/xml/BILLS-119hres173ih.xml", "media_type": "text/xml"}, {"url": "https://www.govinfo.gov/content/pkg/BILLS-119hres173ih/pdf/BILLS-119hres173ih.pdf", "media_type": "application/pdf"}], "date": "2025-02-27", "classification": ""}], "documents": [], "citations": [], "sources": [{"url": "https://www.govinfo.gov/bulkdata/BILLSTATUS/119/hres/BILLSTATUS-119hres173.xml", "note": ""}, {"url": "https://congress.gov/bill/119th-congress/house-resolution/173", "note": ""}], "extras": {"cosponsor_bioguides": ["T000481", "J000309", "O000172", "B001281", "P000617", "M001160", "M001229", "W000822", "J000288", "R000617", "K000385", "B001313", "W000808", "F000476", "T000487"], "sponsor_bioguides": ["K000400"]}, "jurisdiction": {"id": "ocd-jurisdiction/country:us/government", "name": "United States", "classification": "country", "division_id": "ocd-division/country:us"}, "scraped_at": "2025-05-21T00:26:43+00:00", "_id": "4571f042-35da-11f0-8244-a6b901261a72"}