{"name": "Committee on Agriculture, Nutrition, and Forestry Subcommittee on Conservation, Forestry, Natural Resources, and Biotechnology. Hearings held. - HR 471 - Conservation, Climate, Forestry, and Natural Resources Subcommittee", "all_day": false, "start_date": "2025-03-06T05:00:00+00:00", "end_date": "", "status": "confirmed", "classification": "event", "description": "", "upstream_id": "", "location": {"name": "Washington, DC 20004", "note": "", "coordinates": null}, "media": [], "documents": [], "links": [], "participants": [{"name": "Conservation, Climate, Forestry, and Natural Resources Subcommittee", "entity_type": "organization", "note": "participant", "organization_id": "~{\"name\": \"Conservation, Climate, Forestry, and Natural Resources Subcommittee\"}"}], "agenda": [{"description": "Associated Bills", "classification": [], "related_entities": [{"name": "HR 471", "entity_type": "bill", "note": "consideration", "bill_id": "~{\"identifier\": \"HR 471\"}"}], "subjects": [], "media": [], "notes": [], "order": 0, "extras": {}}], "sources": [{"url": "https://www.govinfo.gov/bulkdata/BILLSTATUS/119/hr/BILLSTATUS-119hr471.xml", "note": ""}], "extras": {}, "jurisdiction": {"id": "ocd-jurisdiction/country:us/government", "name": "United States", "classification": "country", "division_id": "ocd-division/country:us"}, "scraped_at": "2025-05-20T23:52:14+00:00", "_id": "7464b45c-35d5-11f0-8244-a6b901261a72"}